pywui_cli/__init__.py
pywui_cli/builder.py
pywui_cli/engine.py
pywui_cli/installer.py
pywui_cli/stubs/cmd
pywui_cli/stubs/icons/pywui.icns
pywui_cli/stubs/icons/pywui.ico
pywui_cli/stubs/icons/pywui.png
pywui_cli/stubs/main.py
pywui_cli/stubs/pywui.conf.json
pywui_cli/style.py
pywui_cli-0.1.7.dist-info/LICENSE
pywui_cli-0.1.7.dist-info/METADATA
pywui_cli-0.1.7.dist-info/WHEEL
pywui_cli-0.1.7.dist-info/entry_points.txt
pywui_cli-0.1.7.dist-info/RECORD
