Metadata-Version: 2.1
Name: pywui-cli
Version: 0.1.7
Summary: Pywui CLI for starting pywui project.
Keywords: pywui,pywebview,pyinstaller,tauri,vite
Author: Tsiresy Milà
Author-email: tsiresymila@gmail.com
Requires-Python: >=3.10,<4.0
Classifier: Programming Language :: Python :: 3
Classifier: Programming Language :: Python :: 3.10
Classifier: Programming Language :: Python :: 3.11
Classifier: Programming Language :: Python :: 3.12
Requires-Dist: click (>=8.1.7,<9.0.0)
Requires-Dist: minijinja (>=2.2.0,<3.0.0)
Requires-Dist: rich-click (>=1.8.3,<2.0.0)
Requires-Dist: ujson (>=5.10.0,<6.0.0)
Requires-Dist: yaspin (>=3.1.0,<4.0.0)
